agent_pgep.py
setup.cfg
setup.py
agent.pgep.egg-info/PKG-INFO
agent.pgep.egg-info/SOURCES.txt
agent.pgep.egg-info/dependency_links.txt
agent.pgep.egg-info/entry_points.txt
agent.pgep.egg-info/requires.txt
agent.pgep.egg-info/top_level.txt