Metadata-Version: 1.0
Name: agent.pgep
Version: 0.2.1
Summary: Rackspace Cloud Monitoring plugin for PostgreSQL       endpoints as an agent.plugin type of check.
Home-page: https://github.com/vickleford/agent.pgep
Author: Vic Watkins
Author-email: vic.watkins@rackspace.com
License: UNKNOWN
Platform: UNKNOWN
